array_api_jax_compat/__init__.py
array_api_jax_compat/_constants.py
array_api_jax_compat/_creation_functions.py
array_api_jax_compat/_data_type_functions.py
array_api_jax_compat/_dispatch.py
array_api_jax_compat/_elementwise_functions.py
array_api_jax_compat/_indexing_functions.py
array_api_jax_compat/_linear_algebra_functions.py
array_api_jax_compat/_manipulation_functions.py
array_api_jax_compat/_searching_functions.py
array_api_jax_compat/_set_functions.py
array_api_jax_compat/_sorting_functions.py
array_api_jax_compat/_statistical_functions.py
array_api_jax_compat/_types.py
array_api_jax_compat/_utility_functions.py
array_api_jax_compat/_utils.py
array_api_jax_compat/_version.py
array_api_jax_compat/_version.pyi
array_api_jax_compat/fft.py
array_api_jax_compat/linalg.py
array_api_jax_compat/py.typed
array_api_jax_compat-0.13.dist-info/METADATA
array_api_jax_compat-0.13.dist-info/WHEEL
array_api_jax_compat-0.13.dist-info/licenses/LICENSE
array_api_jax_compat-0.13.dist-info/RECORD
