Metadata-Version: 2.1
Name: array-api-jax-compat
Version: 0.13
Summary: Array-API JAX compatibility
Project-URL: Homepage, https://github.com/GalacticDynamics/array-api-jax-compat
Project-URL: Bug Tracker, https://github.com/GalacticDynamics/array-api-jax-compat/issues
Project-URL: Discussions, https://github.com/GalacticDynamics/array-api-jax-compat/discussions
Project-URL: Changelog, https://github.com/GalacticDynamics/array-api-jax-compat/releases
Author-email: Nathaniel Starkman <nstarman@users.noreply.github.com>
License-File: LICENSE
Classifier: Development Status :: 1 - Planning
Classifier: Intended Audience :: Developers
Classifier: Intended Audience :: Science/Research
Classifier: License :: OSI Approved :: BSD License
Classifier: Operating System :: OS Independent
Classifier: Programming Language :: Python
Classifier: Programming Language :: Python :: 3
Classifier: Programming Language :: Python :: 3 :: Only
Classifier: Programming Language :: Python :: 3.10
Classifier: Programming Language :: Python :: 3.11
Classifier: Programming Language :: Python :: 3.12
Classifier: Topic :: Scientific/Engineering
Classifier: Typing :: Typed
Requires-Python: >=3.10
Requires-Dist: jax
Requires-Dist: jaxlib
Requires-Dist: plum-dispatch
Requires-Dist: quax>=0.0.3
Provides-Extra: dev
Requires-Dist: pytest-cov>=3; extra == 'dev'
Requires-Dist: pytest>=6; extra == 'dev'
Provides-Extra: docs
Requires-Dist: furo>=2023.08.17; extra == 'docs'
Requires-Dist: myst-parser>=0.13; extra == 'docs'
Requires-Dist: sphinx-autodoc-typehints; extra == 'docs'
Requires-Dist: sphinx-copybutton; extra == 'docs'
Requires-Dist: sphinx>=7.0; extra == 'docs'
Provides-Extra: test
Requires-Dist: pytest-cov>=3; extra == 'test'
Requires-Dist: pytest>=6; extra == 'test'
